galaxy_upload/__init__.py
galaxy_upload/history.py
galaxy_upload/upload.py
galaxy_upload-1.0.1.dist-info/LICENSE
galaxy_upload-1.0.1.dist-info/METADATA
galaxy_upload-1.0.1.dist-info/WHEEL
galaxy_upload-1.0.1.dist-info/entry_points.txt
galaxy_upload-1.0.1.dist-info/top_level.txt
galaxy_upload-1.0.1.dist-info/RECORD
