Metadata-Version: 2.1
Name: galaxy-upload
Version: 1.0.1
Summary: Galaxy Upload Utility
Home-page: https://github.com/galaxyproject/galaxy-upload
Author: Galaxy Project and Community
Author-email: galaxy-committers@lists.galaxyproject.org
License: MIT
Project-URL: Bug Tracker, https://github.com/galaxyproject/galaxy-upload/issues
Project-URL: Documentation, https://galaxy-upload.readthedocs.io/
Project-URL: Source Code, https://github.com/galaxyproject/galaxy-upload
Keywords: Galaxy
Classifier: Development Status :: 5 - Production/Stable
Classifier: Environment :: Console
Classifier: Intended Audience :: Developers
Classifier: License :: OSI Approved :: Academic Free License (AFL)
Classifier: Natural Language :: English
Classifier: Operating System :: POSIX
Classifier: Programming Language :: Python :: 3
Classifier: Programming Language :: Python :: 3.7
Classifier: Programming Language :: Python :: 3.8
Classifier: Programming Language :: Python :: 3.9
Classifier: Programming Language :: Python :: 3.10
Classifier: Programming Language :: Python :: 3.11
Classifier: Topic :: Software Development
Requires-Python: >=3.7
License-File: LICENSE
Requires-Dist: bioblend (>=0.18.0)
Requires-Dist: click
Requires-Dist: click-option-group
Requires-Dist: rich
Requires-Dist: tuspy (!=1.0.1,>=1.0.0)
